odoo/addons/base_ir_actions_sequence/README.rst
odoo/addons/base_ir_actions_sequence/__init__.py
odoo/addons/base_ir_actions_sequence/__manifest__.py
odoo/addons/base_ir_actions_sequence/i18n/base_ir_actions_sequence.pot
odoo/addons/base_ir_actions_sequence/models/__init__.py
odoo/addons/base_ir_actions_sequence/models/ir_actions.py
odoo/addons/base_ir_actions_sequence/static/description/icon.png
odoo/addons/base_ir_actions_sequence/static/description/index.html
odoo/addons/base_ir_actions_sequence/views/actions_views.xml
odoo13_addon_base_ir_actions_sequence-13.0.1.0.1.dist-info/METADATA
odoo13_addon_base_ir_actions_sequence-13.0.1.0.1.dist-info/WHEEL
odoo13_addon_base_ir_actions_sequence-13.0.1.0.1.dist-info/top_level.txt
odoo13_addon_base_ir_actions_sequence-13.0.1.0.1.dist-info/RECORD
